README.md
setup.py
geo_measures.egg-info/PKG-INFO
geo_measures.egg-info/SOURCES.txt
geo_measures.egg-info/dependency_links.txt
geo_measures.egg-info/entry_points.txt
geo_measures.egg-info/not-zip-safe
geo_measures.egg-info/requires.txt
geo_measures.egg-info/top_level.txt
geo_measures/scripts/geo_main.py