Metadata-Version: 2.1
Name: geo-measures
Version: 0.6
Summary: The 'Geometric Measures' script that was developed to carry out geometric analysis on protein structures.
Home-page: https://github.com/lkagami/geo_measures
Author: Luciano Porto Kagami
Author-email: lucianopkagami@hotmail.com
License: UNKNOWN
Keywords: geo_measures
Platform: UNKNOWN
Classifier: Natural Language :: English
Classifier: Programming Language :: Python :: 3.6
Classifier: Programming Language :: Python :: 3.7
Classifier: License :: OSI Approved :: MIT License
Classifier: Operating System :: OS Independent
